commonocean_rules-1.0.3.data/data/LICENSE
commonocean_rules-1.0.3.data/data/config_ship.yaml
commonocean_rules-1.0.3.data/data/traffic_rules_ship.yaml
commonocean_rules-1.0.3.dist-info/licenses/LICENSE
rules/__init__.py
rules/config_ship.yaml
rules/main.py
rules/solution_viz.py
rules/traffic_rules_ship.yaml
rules/common/__init__.py
rules/common/commonocean_evaluation_ship.py
rules/common/helper.py
rules/common/ship.py
rules/common/utils_ship.py
rules/monitor/__init__.py
rules/monitor/monitor_interface_mtl_forward.py
rules/monitor/traffic_rule_dispatcher_ship.py
rules/predicates/__init__.py
rules/predicates/general_predicates_ship.py
rules/predicates/position_predicates_ship.py
rules/predicates/predicate_collection_ship.py
rules/predicates/velocity_predicates_ship.py
commonocean_rules-1.0.3.dist-info/METADATA
commonocean_rules-1.0.3.dist-info/WHEEL
commonocean_rules-1.0.3.dist-info/top_level.txt
commonocean_rules-1.0.3.dist-info/RECORD
