Metadata-Version: 2.4
Name: commonocean-rules
Version: 1.0.3
Summary: Implementation of traffic rule monitor for ships
Home-page: https://commonocean.cps.cit.tum.de/
Author: Cyber-Physical Systems Group, Technical University of Munich
Author-email: commonocean@lists.lrz.de
License: GNU General Public License v3.0
Keywords: rule monitor for ships
Classifier: Programming Language :: Python :: 3.8
Classifier: License :: OSI Approved :: GNU General Public License v3 (GPLv3)
Classifier: Operating System :: POSIX :: Linux
Classifier: Operating System :: MacOS
License-File: LICENSE
Requires-Dist: commonocean-io>=2025.1
Requires-Dist: python-monitors>=0.1.1
Requires-Dist: scipy
Requires-Dist: numpy>=1.16.4
Requires-Dist: metric-temporal-logic>=0.1.4
Requires-Dist: matplotlib>=2.5.0
Requires-Dist: ruamel.yaml>=0.16.10
Requires-Dist: bezier>=2020.2.3
Requires-Dist: antlr4-python3-runtime>=4.7.2
Dynamic: author
Dynamic: author-email
Dynamic: classifier
Dynamic: description
Dynamic: description-content-type
Dynamic: home-page
Dynamic: keywords
Dynamic: license
Dynamic: license-file
Dynamic: requires-dist
Dynamic: summary
